ARConstants/__init__.py
ARConstants/Math/__init__.py
ARConstants/Space/__init__.py
ARConstants/Space/Moons/__init__.py
ARConstants/Space/Moons/Actaea/__init__.py
ARConstants/Space/Moons/Adrastea/__init__.py
ARConstants/Space/Moons/Aegaeon/__init__.py
ARConstants/Space/Moons/Aegir/__init__.py
ARConstants/Space/Moons/Aitne/__init__.py
ARConstants/Space/Moons/Albiorix/__init__.py
ARConstants/Space/Moons/Amalthea/__init__.py
ARConstants/Space/Moons/Ananke/__init__.py
ARConstants/Space/Moons/Anthe/__init__.py
ARConstants/Space/Moons/Aoede/__init__.py
ARConstants/Space/Moons/Arche/__init__.py
ARConstants/Space/Moons/Ariel/__init__.py
ARConstants/Space/Moons/Atlas/__init__.py
ARConstants/Space/Moons/Autonoe/__init__.py
ARConstants/Space/Moons/Bebhionn/__init__.py
ARConstants/Space/Moons/Belinda/__init__.py
ARConstants/Space/Moons/Bergelmir/__init__.py
ARConstants/Space/Moons/Bestla/__init__.py
ARConstants/Space/Moons/Bianca/__init__.py
ARConstants/Space/Moons/Caliban/__init__.py
ARConstants/Space/Moons/Callirrhoe/__init__.py
ARConstants/Space/Moons/Callisto/__init__.py
ARConstants/Space/Moons/Calypso/__init__.py
ARConstants/Space/Moons/Carme/__init__.py
ARConstants/Space/Moons/Carpo/__init__.py
ARConstants/Space/Moons/Chaldene/__init__.py
ARConstants/Space/Moons/Charon/__init__.py
ARConstants/Space/Moons/Cordelia/__init__.py
ARConstants/Space/Moons/Cressida/__init__.py
ARConstants/Space/Moons/Cupid/__init__.py
ARConstants/Space/Moons/Cyllene/__init__.py
ARConstants/Space/Moons/Daphnis/__init__.py
ARConstants/Space/Moons/Deimos/__init__.py
ARConstants/Space/Moons/Desdemona/__init__.py
ARConstants/Space/Moons/Despina/__init__.py
ARConstants/Space/Moons/Dia/__init__.py
ARConstants/Space/Moons/Dione/__init__.py
ARConstants/Space/Moons/Dysnomia/__init__.py
ARConstants/Space/Moons/Eirene/__init__.py
ARConstants/Space/Moons/Elara/__init__.py
ARConstants/Space/Moons/Enceladus/__init__.py
ARConstants/Space/Moons/Epimetheus/__init__.py
ARConstants/Space/Moons/Erinome/__init__.py
arconstants-0.3.0.dist-info/METADATA
arconstants-0.3.0.dist-info/WHEEL
arconstants-0.3.0.dist-info/licenses/LICENSE
arconstants-0.3.0.dist-info/RECORD
