Metadata-Version: 2.1
Name: arconstants
Version: 0.3.0
Summary: A collection of constant numbers.
Project-URL: Source, https://github.com/Apollo-Roboto/ApolloRoboto.Constants
Author-email: Apollo-Roboto <Apollo_Roboto@outlook.com>
License: Copyright © 2022 Apollo-Roboto
Keywords: Constants,Generated,Math,Numbers,Planet,Space
Classifier: Operating System :: OS Independent
Classifier: Programming Language :: Python :: 3
